<?xml version='1.0' encoding='utf-8'?>
<!DOCTYPE words SYSTEM "words.dtd">
	<words>
	  
	  <word id="word_1">Keine</word>

	  <word id="word_2">Garantie</word> 
			
				<word id="word_3">Euphorische</word>
			
				<word id="word_4">Beifallsstürme</word>
			
				<word id="word_5">gab</word>
			
				<word id="word_6">es</word>
			
				<word id="word_7">in</word>
			
				<word id="word_8">Fröhden</word>
			
				<word id="word_9">nicht</word>
			
				<word id="word_10">für</word>
			
				<word id="word_11">die</word>
			
				<word id="word_12">Dorferneuerungsplanung</word>
			
				<word id="word_13">.</word>
			
				<word id="word_14">Das</word>
			
				<word id="word_15">war</word>
			
				<word id="word_16">auch</word>
			
				<word id="word_17">kaum</word>
			
				<word id="word_18">zu</word>
			
				<word id="word_19">erwarten</word>
			
				<word id="word_20">,</word>
			
				<word id="word_21">handelt</word>
			
				<word id="word_22">es</word>
			
				<word id="word_23">sich</word>
			
				<word id="word_24">doch</word>
			
				<word id="word_25">um</word>
			
				<word id="word_26">ein</word>
			
				<word id="word_27">Gemeinschaftswerk</word>
			
				<word id="word_28">,</word>
			
				<word id="word_29">an</word>
			
				<word id="word_30">dem</word>
			
				<word id="word_31">die</word>
			
				<word id="word_32">Einwohner</word>
			
				<word id="word_33">mitgewirkt</word>
			
				<word id="word_34">haben</word>
			
				<word id="word_35">.</word>
			
				<word id="word_36">Deshalb</word>
			
				<word id="word_37">blieben</word>
			
				<word id="word_38">auch</word>
			
				<word id="word_39">kaum</word>
			
				<word id="word_40">Fragen</word>
			
				<word id="word_41">offen</word>
			
				<word id="word_42">,</word>
			
				<word id="word_43">zumindest</word>
			
				<word id="word_44">nicht</word>
			
				<word id="word_45">solche</word>
			
				<word id="word_46">,</word>
			
				<word id="word_47">die</word>
			
				<word id="word_48">die</word>
			
				<word id="word_49">Gestaltung</word>
			
				<word id="word_50">der</word>
			
				<word id="word_51">beiden</word>
			
				<word id="word_52">Jüterboger</word>
			
				<word id="word_53">Ortsteile</word>
			
				<word id="word_54">betrifft</word>
			
				<word id="word_55">.</word>
			
				<word id="word_56">Das</word>
			
				<word id="word_57">Interesse</word>
			
				<word id="word_58">an</word>
			
				<word id="word_59">der</word>
			
				<word id="word_60">Planung</word>
			
				<word id="word_61">war</word>
			
				<word id="word_62">groß</word>
			
				<word id="word_63">,</word>
			
				<word id="word_64">die</word>
			
				<word id="word_65">Beteiligung</word>
			
				<word id="word_66">an</word>
			
				<word id="word_67">den</word>
			
				<word id="word_68">Arbeitskreisen</word>
			
				<word id="word_69">hat</word>
			
				<word id="word_70">es</word>
			
				<word id="word_71">gezeigt</word>
			
				<word id="word_72">.</word>
			
				<word id="word_73">Doch</word>
			
				<word id="word_74">die</word>
			
				<word id="word_75">Freude</word>
			
				<word id="word_76">hält</word>
			
				<word id="word_77">sich</word>
			
				<word id="word_78">in</word>
			
				<word id="word_79">Grenzen</word>
			
				<word id="word_80">,</word>
			
				<word id="word_81">denn</word>
			
				<word id="word_82">inzwischen</word>
			
				<word id="word_83">weiß</word>
			
				<word id="word_84">jeder</word>
			
				<word id="word_85">,</word>
			
				<word id="word_86">dass</word>
			
				<word id="word_87">die</word>
			
				<word id="word_88">Fördermittelgießkanne</word>
			
				<word id="word_89">nur</word>
			
				<word id="word_90">noch</word>
			
				<word id="word_91">tröpfchenweise</word>
			
				<word id="word_92">austeilt</word>
			
				<word id="word_93">.</word>
			
				<word id="word_94">Wer</word>
			
				<word id="word_95">auf</word>
			
				<word id="word_96">das</word>
			
				<word id="word_97">Ja-Wort</word>
			
				<word id="word_98">aus</word>
			
				<word id="word_99">Brieselang</word>
			
				<word id="word_100">warten</word>
			
				<word id="word_101">kann</word>
			
				<word id="word_102">,</word>
			
				<word id="word_103">keine</word>
			
				<word id="word_104">Scheu</word>
			
				<word id="word_105">vor</word>
			
				<word id="word_106">seitenlangen</word>
			
				<word id="word_107">Fragebögen</word>
			
				<word id="word_108">hat</word>
			
				<word id="word_109">und</word>
			
				<word id="word_110">in</word>
			
				<word id="word_111">Kauf</word>
			
				<word id="word_112">nimmt</word>
			
				<word id="word_113">,</word>
			
				<word id="word_114">dass</word>
			
				<word id="word_115">er</word>
			
				<word id="word_116">wahrscheinlich</word>
			
				<word id="word_117">nicht</word>
			
				<word id="word_118">billiger</word>
			
				<word id="word_119">wegkommt</word>
			
				<word id="word_120">,</word>
			
				<word id="word_121">als</word>
			
				<word id="word_122">wenn</word>
			
				<word id="word_123">er</word>
			
				<word id="word_124">nach</word>
			
				<word id="word_125">eigenen</word>
			
				<word id="word_126">Vorstellungen</word>
			
				<word id="word_127">die</word>
			
				<word id="word_128">Fassade</word>
			
				<word id="word_129">gestrichen</word>
			
				<word id="word_130">hätte</word>
			
				<word id="word_131">-</word>
			
				<word id="word_132">dem</word>
			
				<word id="word_133">kann</word>
			
				<word id="word_134">bescheinigt</word>
			
				<word id="word_135">werden</word>
			
				<word id="word_136">,</word>
			
				<word id="word_137">dass</word>
			
				<word id="word_138">ihm</word>
			
				<word id="word_139">sein</word>
			
				<word id="word_140">Dorf</word>
			
				<word id="word_141">und</word>
			
				<word id="word_142">dessen</word>
			
				<word id="word_143">Erscheinungsbild</word>
			
				<word id="word_144">am</word>
			
				<word id="word_145">Herzen</word>
			
				<word id="word_146">liegt</word>
			
				<word id="word_147">.</word>
			
				<word id="word_148">Schweren</word>
			
				<word id="word_149">Herzens</word>
			
				<word id="word_150">wird</word>
			
				<word id="word_151">sich</word>
			
				<word id="word_152">die</word>
			
				<word id="word_153">Stadt</word>
			
				<word id="word_154">von</word>
			
				<word id="word_155">ihrem</word>
			
				<word id="word_156">Geld</word>
			
				<word id="word_157">trennen</word>
			
				<word id="word_158">,</word>
			
				<word id="word_159">wenn</word>
			
				<word id="word_160">es</word>
			
				<word id="word_161">nämlich</word>
			
				<word id="word_162">darum</word>
			
				<word id="word_163">geht</word>
			
				<word id="word_164">,</word>
			
				<word id="word_165">die</word>
			
				<word id="word_166">Eigenanteile</word>
			
				<word id="word_167">für</word>
			
				<word id="word_168">bestimmte</word>
			
				<word id="word_169">Vorhaben</word>
			
				<word id="word_170">zur</word>
			
				<word id="word_171">Verfügung</word>
			
				<word id="word_172">zu</word>
			
				<word id="word_173">stellen</word>
			
				<word id="word_174">.</word>
			
				<word id="word_175">Die</word>
			
				<word id="word_176">Dorferneuerungsplanung</word>
			
				<word id="word_177">ist</word>
			
				<word id="word_178">längst</word>
			
				<word id="word_179">keine</word>
			
				<word id="word_180">Garantie</word>
			
				<word id="word_181">mehr</word>
			
				<word id="word_182">für</word>
			
				<word id="word_183">grenzenlosen</word>
			
				<word id="word_184">Geldsegen</word>
			
				<word id="word_185">.</word>
			
				<word id="word_186">So</word>
			
				<word id="word_187">könnte</word>
			
				<word id="word_188">es</word>
			
				<word id="word_189">passieren</word>
			
				<word id="word_190">,</word>
			
				<word id="word_191">dass</word>
			
				<word id="word_192">viele</word>
			
				<word id="word_193">schöne</word>
			
				<word id="word_194">Vorhaben</word>
			
				<word id="word_195">nur</word>
			
				<word id="word_196">Visionen</word>
			
				<word id="word_197">bleiben</word>
			
				<word id="word_198">.</word>
			
        </words>
  