<?xml version='1.0' encoding='utf-8'?>
<!DOCTYPE words SYSTEM "words.dtd">
	<words>
	  <word id="word_1">Feigenblatt</word>

				<word id="word_2">Die</word>
			
				<word id="word_3">Jugendlichen</word>
			
				<word id="word_4">in</word>
			
				<word id="word_5">Zossen</word>
			
				<word id="word_6">wollen</word>
			
				<word id="word_7">ein</word>
			
				<word id="word_8">Musikcafé</word>
			
				<word id="word_9">.</word>
			
				<word id="word_10">Das</word>
			
				<word id="word_11">forderten</word>
			
				<word id="word_12">sie</word>
			
				<word id="word_13">bei</word>
			
				<word id="word_14">der</word>
			
				<word id="word_15">ersten</word>
			
				<word id="word_16">Zossener</word>
			
				<word id="word_17">Runde</word>
			
				<word id="word_18">am</word>
			
				<word id="word_19">Dienstagabend</word>
			
				<word id="word_20">.</word>
			
				<word id="word_21">Dass</word>
			
				<word id="word_22">die</word>
			
				<word id="word_23">Politiker</word>
			
				<word id="word_24">der</word>
			
				<word id="word_25">Stadt</word>
			
				<word id="word_26">dafür</word>
			
				<word id="word_27">Verständnis</word>
			
				<word id="word_28">haben</word>
			
				<word id="word_29">,</word>
			
				<word id="word_30">ist</word>
			
				<word id="word_31">löblich</word>
			
				<word id="word_32">.</word>
			
				<word id="word_33">Mit</word>
			
				<word id="word_34">dem</word>
			
				<word id="word_35">Treffen</word>
			
				<word id="word_36">im</word>
			
				<word id="word_37">Rathaus</word>
			
				<word id="word_38">ist</word>
			
				<word id="word_39">somit</word>
			
				<word id="word_40">auch</word>
			
				<word id="word_41">ein</word>
			
				<word id="word_42">Dialog</word>
			
				<word id="word_43">zwischen</word>
			
				<word id="word_44">den</word>
			
				<word id="word_45">Generationen</word>
			
				<word id="word_46">angestoßen</word>
			
				<word id="word_47">.</word>
			
				<word id="word_48">Dass</word>
			
				<word id="word_49">die</word>
			
				<word id="word_50">beiden</word>
			
				<word id="word_51">geladenen</word>
			
				<word id="word_52">Jugendlichen</word>
			
				<word id="word_53">im</word>
			
				<word id="word_54">Laufe</word>
			
				<word id="word_55">des</word>
			
				<word id="word_56">Abends</word>
			
				<word id="word_57">immer</word>
			
				<word id="word_58">weniger</word>
			
				<word id="word_59">zu</word>
			
				<word id="word_60">Wort</word>
			
				<word id="word_61">kamen</word>
			
				<word id="word_62">,</word>
			
				<word id="word_63">war</word>
			
				<word id="word_64">sicher</word>
			
				<word id="word_65">keine</word>
			
				<word id="word_66">böse</word>
			
				<word id="word_67">Absicht</word>
			
				<word id="word_68">,</word>
			
				<word id="word_69">ärgerlich</word>
			
				<word id="word_70">ist</word>
			
				<word id="word_71">es</word>
			
				<word id="word_72">trotzdem</word>
			
				<word id="word_73">.</word>
			
				<word id="word_74">Und</word>
			
				<word id="word_75">aberwitzig</word>
			
				<word id="word_76">dazu</word>
			
				<word id="word_77">.</word>
			
				<word id="word_78">Es</word>
			
				<word id="word_79">entbehrt</word>
			
				<word id="word_80">nicht</word>
			
				<word id="word_81">der</word>
			
				<word id="word_82">Komik</word>
			
				<word id="word_83">,</word>
			
				<word id="word_84">wenn</word>
			
				<word id="word_85">sich</word>
			
				<word id="word_86">drei</word>
			
				<word id="word_87">Erwachsene</word>
			
				<word id="word_88">-</word>
			
				<word id="word_89">Karola</word>
			
				<word id="word_90">Andrae</word>
			
				<word id="word_91">(</word>
			
				<word id="word_92">Bürgerbündnis/FDP</word>
			
				<word id="word_93">)</word>
			
				<word id="word_94">,</word>
			
				<word id="word_95">Susanne</word>
			
				<word id="word_96">Michler</word>
			
				<word id="word_97">(</word>
			
				<word id="word_98">CDU</word>
			
				<word id="word_99">)</word>
			
				<word id="word_100">und</word>
			
				<word id="word_101">Joachim</word>
			
				<word id="word_102">Zanow</word>
			
				<word id="word_103">(</word>
			
				<word id="word_104">SPD</word>
			
				<word id="word_105">)</word>
			
				<word id="word_106">-</word>
			
				<word id="word_107">darüber</word>
			
				<word id="word_108">streiten</word>
			
				<word id="word_109">,</word>
			
				<word id="word_110">was</word>
			
				<word id="word_111">Jugendliche</word>
			
				<word id="word_112">wollen</word>
			
				<word id="word_113">und</word>
			
				<word id="word_114">brauchen</word>
			
				<word id="word_115">,</word>
			
				<word id="word_116">ohne</word>
			
				<word id="word_117">auf</word>
			
				<word id="word_118">die</word>
			
				<word id="word_119">Idee</word>
			
				<word id="word_120">zu</word>
			
				<word id="word_121">kommen</word>
			
				<word id="word_122">,</word>
			
				<word id="word_123">sie</word>
			
				<word id="word_124">selbst</word>
			
				<word id="word_125">zu</word>
			
				<word id="word_126">fragen</word>
			
				<word id="word_127">.</word>
			
				<word id="word_128">Und</word>
			
				<word id="word_129">das</word>
			
				<word id="word_130">,</word>
			
				<word id="word_131">obwohl</word>
			
				<word id="word_132">sie</word>
			
				<word id="word_133">ihnen</word>
			
				<word id="word_134">gegenüber</word>
			
				<word id="word_135">sitzen</word>
			
				<word id="word_136">.</word>
			
				<word id="word_137">Die</word>
			
				<word id="word_138">Jugendlichen</word>
			
				<word id="word_139">wurden</word>
			
				<word id="word_140">somit</word>
			
				<word id="word_141">zum</word>
			
				<word id="word_142">bloßen</word>
			
				<word id="word_143">Feigenblatt</word>
			
				<word id="word_144">degradiert</word>
			
				<word id="word_145">.</word>
			
				<word id="word_146">Nicht</word>
			
				<word id="word_147">über</word>
			
				<word id="word_148">sondern</word>
			
				<word id="word_149">mit</word>
			
				<word id="word_150">ihnen</word>
			
				<word id="word_151">hätten</word>
			
				<word id="word_152">die</word>
			
				<word id="word_153">Politiker</word>
			
				<word id="word_154">reden</word>
			
				<word id="word_155">sollen</word>
			
				<word id="word_156">.</word>
			
				<word id="word_157">Damit</word>
			
				<word id="word_158">ist</word>
			
				<word id="word_159">eine</word>
			
				<word id="word_160">große</word>
			
				<word id="word_161">Chance</word>
			
				<word id="word_162">vertan</word>
			
				<word id="word_163">.</word>
			
				<word id="word_164">Vielleicht</word>
			
				<word id="word_165">klappt</word>
			
				<word id="word_166">es</word>
			
				<word id="word_167">bei</word>
			
				<word id="word_168">der</word>
			
				<word id="word_169">nächsten</word>
			
				<word id="word_170">Runde</word>
			
				<word id="word_171">Anfang</word>
			
				<word id="word_172">2002</word>
			
				<word id="word_173">.</word>
			
				<word id="word_174">Dann</word>
			
				<word id="word_175">werden</word>
			
				<word id="word_176">auch</word>
			
				<word id="word_177">mehr</word>
			
				<word id="word_178">Jugendliche</word>
			
				<word id="word_179">eingeladen</word>
			
				<word id="word_180">.</word>
			
				<word id="word_181">In</word>
			
				<word id="word_182">der</word>
			
				<word id="word_183">Gruppe</word>
			
				<word id="word_184">können</word>
			
				<word id="word_185">sie</word>
			
				<word id="word_186">sich</word>
			
				<word id="word_187">hoffentlich</word>
			
				<word id="word_188">mehr</word>
			
				<word id="word_189">Gehör</word>
			
				<word id="word_190">verschaffen</word>
			
				<word id="word_191">.</word>
			
				<word id="word_192">Vielleicht</word>
			
				<word id="word_193">finden</word>
			
				<word id="word_194">dann</word>
			
				<word id="word_195">auch</word>
			
				<word id="word_196">Vertreter</word>
			
				<word id="word_197">von</word>
			
				<word id="word_198">PDS</word>
			
				<word id="word_199">und</word>
			
				<word id="word_200">Gewerbeverein</word>
			
				<word id="word_201">ihren</word>
			
				<word id="word_202">Weg</word>
			
				<word id="word_203">ins</word>
			
				<word id="word_204">Rathaus</word>
			
				<word id="word_205">.</word>
			
				<word id="word_206">Die</word>
			
				<word id="word_207">glänzten</word>
			
				<word id="word_208">diesmal</word>
			
				<word id="word_209">noch</word>
			
				<word id="word_210">mit</word>
			
				<word id="word_211">Abwesenheit</word>
			
				<word id="word_212">.</word>
			
        </words>
  