<?xml version="1.0"?>
<!DOCTYPE markables SYSTEM "markables.dtd">
<markables xmlns="www.eml.org/NameSpaces/primmark">
<markable id="markable_18" span="word_136..word_138" phrase_type="np"  anaphor_antecedent="empty"  type="none"  complex_np="no"  np_form="ne"  referentiality="discourse-new"  grammatical_role="sbj"  ambiguity="not_ambig"  dir_speech="text_level" />
<markable id="markable_28" span="word_109..word_112" phrase_type="np"  anaphor_antecedent="empty"  type="none"  complex_np="yes"  np_form="defnp"  referentiality="discourse-new"  grammatical_role="other"  ambiguity="not_ambig"  dir_speech="text_level" />
<markable id="markable_5" span="word_40..word_52" phrase_type="np"  anaphor_antecedent="empty"  type="none"  complex_np="yes"  np_form="defnp"  referentiality="discourse-new"  grammatical_role="sbj"  ambiguity="not_ambig"  dir_speech="text_level" />
<markable id="markable_20" span="word_148..word_149" phrase_type="np"  anaphor_antecedent="markable_1"  type="anaphoric"  complex_np="no"  np_form="defnp"  referentiality="referring"  grammatical_role="sbj"  ambiguity="not_ambig"  anaphor_type="anaphor_nominal"  dir_speech="text_level" />
<markable id="markable_17" span="word_111..word_112" phrase_type="np"  anaphor_antecedent="markable_13"  type="anaphoric"  complex_np="no"  np_form="defnp"  referentiality="referring"  grammatical_role="indir-obj"  ambiguity="not_ambig"  anaphor_type="anaphor_nominal"  dir_speech="text_level" />
<markable id="markable_23" span="word_33" phrase_type="np"  anaphor_antecedent="markable_4"  type="anaphoric"  complex_np="no"  np_form="ppos"  referentiality="referring"  grammatical_role="other"  ambiguity="not_ambig"  anaphor_type="anaphor_nominal"  dir_speech="text_level" />
<markable id="markable_8" span="word_51..word_52" phrase_type="np"  anaphor_antecedent="markable_7"  type="anaphoric"  complex_np="no"  np_form="defnp"  referentiality="referring"  grammatical_role="indir-obj"  ambiguity="not_ambig"  anaphor_type="anaphor_nominal"  dir_speech="text_level" />
<markable id="markable_16" span="word_108..word_112" phrase_type="pp"  anaphor_antecedent="markable_14"  type="anaphoric"  complex_np="yes"  np_form="defnp"  referentiality="referring"  grammatical_role="other"  ambiguity="not_ambig"  anaphor_type="anaphor_nominal"  dir_speech="text_level" />
<markable id="markable_26" span="word_43..word_44" phrase_type="np"  anaphor_antecedent="empty"  type="none"  complex_np="no"  np_form="defnp"  referentiality="discourse-new"  grammatical_role="other"  ambiguity="not_ambig"  dir_speech="text_level" />
<markable id="markable_7" span="word_29..word_31" phrase_type="np"  anaphor_antecedent="empty"  type="none"  complex_np="no"  np_form="defnp"  referentiality="discourse-new"  grammatical_role="indir-obj"  ambiguity="not_ambig"  dir_speech="text_level" />
<markable id="markable_19" span="word_141..word_143" phrase_type="pp"  anaphor_antecedent="empty"  type="none"  complex_np="no"  np_form="defnp"  referentiality="discourse-new"  grammatical_role="other"  ambiguity="not_ambig"  dir_speech="text_level" />
<markable id="markable_25" span="word_38" phrase_type="np"  anaphor_antecedent="empty"  type="none"  complex_np="no"  np_form="pds"  referentiality="referring"  grammatical_role="other"  ambiguity="not_ambig"  dir_speech="text_level" />
<markable id="markable_14" span="word_96..word_98" phrase_type="pp"  anaphor_antecedent="empty"  type="none"  complex_np="no"  np_form="defnp"  referentiality="discourse-new"  grammatical_role="other"  ambiguity="not_ambig"  dir_speech="text_level" />
<markable id="markable_11" span="word_62" phrase_type="np"  anaphor_antecedent="markable_10"  type="anaphoric"  complex_np="no"  np_form="pper"  referentiality="referring"  grammatical_role="sbj"  ambiguity="not_ambig"  anaphor_type="anaphor_nominal"  dir_speech="text_level" />
<markable id="markable_6" span="word_47..word_48" phrase_type="np"  anaphor_antecedent="markable_23"  type="anaphoric"  complex_np="no"  np_form="defnp"  referentiality="referring"  grammatical_role="other"  ambiguity="not_ambig"  anaphor_type="anaphor_nominal"  dir_speech="text_level" />
<markable id="markable_13" span="word_89..word_90" phrase_type="np"  anaphor_antecedent="markable_6"  type="anaphoric"  complex_np="no"  np_form="defnp"  referentiality="referring"  grammatical_role="other"  ambiguity="not_ambig"  anaphor_type="anaphor_nominal"  dir_speech="text_level" />
<markable id="markable_24" span="word_33..word_34" phrase_type="np"  anaphor_antecedent="empty"  type="none"  complex_np="no"  np_form="defnp"  referentiality="discourse-new"  grammatical_role="dir-obj"  ambiguity="not_ambig"  dir_speech="text_level" />
<markable id="markable_1" span="word_17..word_20" phrase_type="np"  anaphor_antecedent="empty"  type="none"  complex_np="yes"  np_form="defnp"  referentiality="discourse-new"  grammatical_role="sbj"  ambiguity="not_ambig"  dir_speech="text_level" />
<markable id="markable_12" span="word_87..word_94" phrase_type="np"  anaphor_antecedent="empty"  type="none"  complex_np="yes"  np_form="defnp"  referentiality="discourse-new"  grammatical_role="sbj"  ambiguity="not_ambig"  dir_speech="text_level" />
<markable id="markable_4" span="word_25..word_26" phrase_type="np"  anaphor_antecedent="markable_2"  type="anaphoric"  complex_np="yes"  np_form="defnp"  referentiality="referring"  grammatical_role="sbj"  ambiguity="not_ambig"  anaphor_type="anaphor_nominal"  dir_speech="text_level" />
<markable id="markable_27" span="word_45..word_48" phrase_type="np"  anaphor_antecedent="empty"  type="none"  complex_np="yes"  np_form="defnp"  referentiality="discourse-new"  grammatical_role="other"  ambiguity="not_ambig"  dir_speech="text_level" />
<markable id="markable_15" span="word_104..word_105" phrase_type="np"  anaphor_antecedent="empty"  type="none"  complex_np="no"  np_form="defnp"  referentiality="discourse-new"  grammatical_role="sbj"  ambiguity="not_ambig"  dir_speech="text_level" />
<markable id="markable_21" span="word_150..word_152" phrase_type="pp"  anaphor_antecedent="markable_19"  type="anaphoric"  complex_np="no"  np_form="defnp"  referentiality="referring"  grammatical_role="other"  ambiguity="not_ambig"  anaphor_type="anaphor_nominal"  dir_speech="text_level" />
<markable id="markable_10" span="word_57..word_58" phrase_type="np"  anaphor_antecedent="empty"  type="none"  complex_np="no"  np_form="defnp"  referentiality="discourse-new"  grammatical_role="other"  ambiguity="not_ambig"  dir_speech="text_level" />
<markable id="markable_2" span="word_19..word_20" phrase_type="np"  anaphor_antecedent="empty"  type="none"  complex_np="no"  np_form="defnp"  referentiality="discourse-new"  grammatical_role="other"  ambiguity="not_ambig"  dir_speech="text_level" />
<markable id="markable_22" span="word_159..word_161" phrase_type="pp"  anaphor_antecedent="markable_21"  type="anaphoric"  complex_np="no"  np_form="defnp"  referentiality="referring"  grammatical_role="other"  ambiguity="not_ambig"  anaphor_type="anaphor_nominal"  dir_speech="text_level" />
<markable id="markable_29" span="word_122..word_123" phrase_type="np"  anaphor_antecedent="empty"  type="none"  complex_np="no"  np_form="defnp"  referentiality="discourse-new"  grammatical_role="sbj"  ambiguity="not_ambig"  dir_speech="text_level" />
</markables>